sftoolbox/__init__.py
sftoolbox/actions.py
sftoolbox/content.py
sftoolbox/engineinterface.py
sftoolbox/panels.py
sftoolbox/project.py
sftoolbox/utils.py
sftoolbox-0.2.0.dist-info/DESCRIPTION.rst
sftoolbox-0.2.0.dist-info/LICENSE.txt
sftoolbox-0.2.0.dist-info/METADATA
sftoolbox-0.2.0.dist-info/RECORD
sftoolbox-0.2.0.dist-info/WHEEL
sftoolbox-0.2.0.dist-info/entry_points.txt
sftoolbox-0.2.0.dist-info/metadata.json
sftoolbox-0.2.0.dist-info/top_level.txt
sftoolboxqt/__init__.py
sftoolboxqt/cli.py
sftoolboxqt/engineinterface.py
sftoolboxqt/qtguipyside.py
sftoolboxqt/qtguipyside2.py
sftoolboxqt/styles.py
sftoolboxqt/utils.py
sftoolboxqt/widgets.py
