Metadata-Version: 2.0
Name: sftoolbox
Version: 0.2.0
Summary: sharing tools and snippets for VFX and animation
Home-page: https://github.com/svenfraeys/sftoolbox/
Author: Sven Fraeys
Author-email: sven.fraey@gmail.com
License: MIT
Platform: any
Requires-Dist: pyside
Requires-Dist: PyYaml
Provides-Extra: dev
Requires-Dist: pytest; extra == 'dev'
Requires-Dist: coverage; extra == 'dev'
Requires-Dist: tox; extra == 'dev'
